{
  "users": [
    {
      "id": "d0e1",
      "username": "bob.johnson@example.com",
      "password": "AdminSecure456!"
    },
    {
      "id": "9adc",
      "username": "admin@admin.com",
      "password": "admin"
    },
    {
      "id": "2631",
      "username": "admin@admin.com",
      "password": "admin"
    },
    {
      "id": "ce07",
      "username": "admin@admin.com",
      "password": "admin"
    },
    {
      "id": "a775",
      "username": "admin@admin.com",
      "password": "admin"
    },
    {
      "id": "2829",
      "username": "admin@admin.com",
      "password": "admin"
    },
    {
      "id": "cec7",
      "username": "admin@admin.com",
      "password": "admin"
    },
    {
      "id": "70ec",
      "username": "admin@admin.com",
      "password": "admin"
    },
    {
      "id": "df81",
      "username": "admin@admin.com",
      "password": "admin"
    },
    {
      "id": "0f85",
      "username": "admin@admin.com",
      "password": "admin"
    },
    {
      "id": "dbb3",
      "username": "admin@admin.com",
      "password": "admin"
    },
    {
      "id": "52b9",
      "username": "admin@admin.com",
      "password": "admin"
    },
    {
      "id": "97ed",
      "username": "admin@admin.com",
      "password": "admin"
    },
    {
      "id": "11b8",
      "username": "admin@admin.com",
      "password": "admin"
    },
    {
      "id": "39e5",
      "username": "admin@admin.com",
      "password": "admin"
    }
  ]
}